capture/Dockerfile
capture/VERSION
capture/__init__.py
capture/__main__.py
capture/requirements.txt
capture/streamer.py
cuwb_stream/Dockerfile
cuwb_stream/Makefile
cuwb_stream/README.md
cuwb_stream/VERSION
cuwb_stream/__init__.py
cuwb_stream/collector.py
cuwb_stream/development.txt
cuwb_stream/network.py
cuwb_stream/requirements.txt
cuwb_stream/tests/__init__.py
cuwb_stream/tests/test_collector.py
cuwb_stream/tools/__init__.py
cuwb_stream/tools/__main__.py
cuwb_stream/tools/snooplogg.py
wf_camera_utils-1.0.28.dist-info/WHEEL
wf_camera_utils-1.0.28.dist-info/METADATA
wf_camera_utils-1.0.28.dist-info/RECORD
