Metadata-Version: 2.1
Name: wf-camera-utils
Version: 1.0.28
Summary: utilities for wildflower cameras and raspberry pi
License: MIT
Author: Paul J DeCoursey
Author-email: paul@decoursey.net
Requires-Python: >=3.9,<4.0
Classifier: License :: OSI Approved :: MIT License
Classifier: Programming Language :: Python :: 3
Classifier: Programming Language :: Python :: 3.9
Classifier: Programming Language :: Python :: 3.10
Requires-Dist: ffmpeg-python (==0.2.0)
Requires-Dist: influx_line_protocol (>=0.1.5)
Requires-Dist: minio (>=7.1.12)
Requires-Dist: python-json-logger (>=2.0.4)
Requires-Dist: pyyaml (>=6.0)
